mwaa_dr/__init__.py
mwaa_dr/backup_metadata.py
mwaa_dr/cleanup_metadata.py
mwaa_dr/restore_metadata.py
mwaa_dr/framework/__init__.py
mwaa_dr/framework/factory/__init__.py
mwaa_dr/framework/factory/base_dr_factory.py
mwaa_dr/framework/factory/default_dag_factory.py
mwaa_dr/framework/model/__init__.py
mwaa_dr/framework/model/active_dag_table.py
mwaa_dr/framework/model/base_table.py
mwaa_dr/framework/model/connection_table.py
mwaa_dr/framework/model/dependency_model.py
mwaa_dr/framework/model/variable_table.py
mwaa_dr/v_2_4/__init__.py
mwaa_dr/v_2_4/dr_factory.py
mwaa_dr/v_2_5/__init__.py
mwaa_dr/v_2_5/dr_factory.py
mwaa_dr/v_2_6/__init__.py
mwaa_dr/v_2_6/dr_factory.py
mwaa_dr/v_2_7/__init__.py
mwaa_dr/v_2_7/dr_factory.py
mwaa_dr/v_2_8/__init__.py
mwaa_dr/v_2_8/dr_factory.py
mwaa_dr-2.0.1.dist-info/LICENSE.md
mwaa_dr-2.0.1.dist-info/METADATA
mwaa_dr-2.0.1.dist-info/WHEEL
mwaa_dr-2.0.1.dist-info/top_level.txt
mwaa_dr-2.0.1.dist-info/RECORD
