Metadata-Version: 2.1
Name: mwaa_dr
Version: 2.0.1
Summary: DR Solution for Amazon Managed Workflows for Apache Airflow (MWAA)
License: Copyright Amazon.com, Inc. or its affiliates. All Rights Reserved.
Project-URL: Homepage, https://github.com/aws-samples/mwaa-disaster-recovery
Project-URL: Documentation, https://github.com/aws-samples/mwaa-disaster-recovery/blob/main/PYPIDOC.md
Project-URL: Repository, https://github.com/aws-samples/mwaa-disaster-recovery.git
Project-URL: Bug Tracker, https://github.com/aws-samples/mwaa-disaster-recovery/issues
Project-URL: Changelog, https://github.com/aws-samples/mwaa-disaster-recovery/blob/main/CHANGELOG.md
Keywords: MWAA,airflow,disaster,recovery,DR
Classifier: Development Status :: 5 - Production/Stable
Classifier: Programming Language :: Python
Requires-Python: >=3.7
License-File: LICENSE.md
Requires-Dist: smart-open >=7.0.4
